iota/__init__.py
iota/api.py
iota/codecs.py
iota/exceptions.py
iota/filters.py
iota/json.py
iota/trits.py
iota/types.py
iota/adapter/__init__.py
iota/adapter/sandbox.py
iota/adapter/wrappers.py
iota/bin/__init__.py
iota/bin/repl.py
iota/commands/__init__.py
iota/commands/core/__init__.py
iota/commands/core/add_neighbors.py
iota/commands/core/attach_to_tangle.py
iota/commands/core/broadcast_transactions.py
iota/commands/core/check_consistency.py
iota/commands/core/find_transactions.py
iota/commands/core/get_balances.py
iota/commands/core/get_inclusion_states.py
iota/commands/core/get_missing_transactions.py
iota/commands/core/get_neighbors.py
iota/commands/core/get_node_api_configuration.py
iota/commands/core/get_node_info.py
iota/commands/core/get_tips.py
iota/commands/core/get_transactions_to_approve.py
iota/commands/core/get_trytes.py
iota/commands/core/interrupt_attaching_to_tangle.py
iota/commands/core/remove_neighbors.py
iota/commands/core/store_transactions.py
iota/commands/core/were_addresses_spent_from.py
iota/commands/extended/__init__.py
iota/commands/extended/broadcast_and_store.py
iota/commands/extended/find_transaction_objects.py
iota/commands/extended/get_account_data.py
iota/commands/extended/get_bundles.py
iota/commands/extended/get_inputs.py
iota/commands/extended/get_latest_inclusion.py
iota/commands/extended/get_new_addresses.py
iota/commands/extended/get_transaction_objects.py
iota/commands/extended/get_transfers.py
iota/commands/extended/helpers.py
iota/commands/extended/is_reattachable.py
iota/commands/extended/prepare_transfer.py
iota/commands/extended/promote_transaction.py
iota/commands/extended/replay_bundle.py
iota/commands/extended/send_transfer.py
iota/commands/extended/send_trytes.py
iota/commands/extended/utils.py
iota/crypto/__init__.py
iota/crypto/addresses.py
iota/crypto/pycurl.py
iota/crypto/signing.py
iota/crypto/types.py
iota/crypto/kerl/__init__.py
iota/crypto/kerl/conv.py
iota/crypto/kerl/pykerl.py
iota/multisig/__init__.py
PyOTA-2.1.0.dist-info/LICENSE
PyOTA-2.1.0.dist-info/METADATA
PyOTA-2.1.0.dist-info/WHEEL
PyOTA-2.1.0.dist-info/entry_points.txt
PyOTA-2.1.0.dist-info/top_level.txt
PyOTA-2.1.0.dist-info/RECORD
