Metadata-Version: 2.1
Name: PyOTA
Version: 2.1.0
Summary: IOTA API library for Python
Home-page: https://github.com/iotaledger/iota.py
Author: Phoenix Zerin
Author-email: phx@phx.ph
License: MIT
Keywords: iota,tangle,iot,internet of things,api,library,cryptocurrency,balanced ternary
Platform: UNKNOWN
Classifier: Development Status :: 5 - Production/Stable
Classifier: Intended Audience :: Developers
Classifier: License :: OSI Approved :: MIT License
Classifier: Programming Language :: Python :: 2
Classifier: Programming Language :: Python :: 2.7
Classifier: Programming Language :: Python :: 3
Classifier: Programming Language :: Python :: 3.5
Classifier: Programming Language :: Python :: 3.6
Classifier: Programming Language :: Python :: 3.7
Classifier: Topic :: Software Development :: Libraries :: Python Modules
Provides-Extra: ccurl
Provides-Extra: pow
Provides-Extra: docs-builder
Provides-Extra: test-runner
